{
  "app": {
    "connectionFailed": "З'єднання з сервером не працює належним чином, і ви більше не можете отримувати запити на консультацію. Якщо проблема залишається, будь ласка, оновіть сторінку.",
    "consultationHistory": "Історія консультацій",
    "dashboard": "Панель керування",
    "invites": "Запрошення",
    "openedConsultation": "Відкриті консультації",
    "reconnected": "Ви знову підключені",
    "refresh": "Оновити",
    "support": "Підтримка",
    "testVideoSound": "Тестування відео/звуку",
    "waitingRoom": "Зала очікування"
  },
  "cgu": {
    "backToHome": "Назад",
    "before": "перш ніж ви зможете використовувати {{branding}}.",
    "country": "Країна",
    "description": "Умови доступу",
    "notConfigured": "Умови та положення ще не налаштовані.",
    "pleaseAccept": "Ви маєте прийняти {{terms}}, щоб використовувати {{branding}}",
    "selectCountry": "Визначте вашу країну та мову:",
    "submit": "Підтвердити",
    "terms": "Умови та положення",
    "termsAndConditions": "Умови та положення",
    "youHaveTo": "Ви маєте прийняти"
  },
  "chat": {
    "IMADTeam": "Команда IMAD",
    "addNotePlaceholder": "Введіть вашу нотатку...",
    "addNoteTitle": "Додати нотатку",
    "cancelAddNote": "Скасувати",
    "cancelCall": "Скасувати дзвінок",
    "doctor": "Медсестра",
    "duration": "Тривалість",
    "email": "Електронна пошта",
    "endDateTime": "Дата/час завершення",
    "generalInformation": "ЗАГАЛЬНА ІНФОРМАЦІЯ",
    "guest": "Гість",
    "inviteExpert": "Запросити колегу",
    "joinVideoCall": "Приєднатися до відео",
    "needAccess": "Нам потрібен доступ до вашого мікрофону для продовження дзвінка. Будь ласка, надайте доступ до мікрофону.",
    "notdefined": "Не визначено",
    "nurse": "Медсестра",
    "patientBirthday": "Дата народження користувача послуг",
    "patientFirstnameAndLastname": "Ім'я користувача послуг",
    "patientInvitedAt": "Користувача послуг запрошено о",
    "permissionRequired": "Потрібен дозвіл на мікрофон",
    "phoneNumber": "Номер телефону",
    "requestedBy": "Запитано від",
    "retryPermission": "Повторити дозвіл",
    "saveNote": "Зберегти",
    "sex": "Стать",
    "startDateTime": "Дата/час початку",
    "takeOwnership": "Отримати право власності",
    "textMessagesOnlySentToPatientWarning": "У випадку телеконсультації з користувачем послуг повідомлення та вкладення, надіслані тут, видно лише користувачу послуг з міркувань конфіденційності",
    "transferOwnershipCancel": "Скасувати",
    "transferOwnershipConfirm": "Так, отримати право власності",
    "transferOwnershipError": "Не вдалося передати право власності",
    "transferOwnershipQuestion": "Ви впевнені, що хочете отримати право власності на цю сесію?",
    "transferOwnershipSuccess": "Право власності успішно передано",
    "transferOwnershipTitle": "Передача права власності",
    "translator": "Перекладач",
    "translatorContactDetails": "Контактні дані перекладача",
    "videoAudioAccepted": "Відео-аудіо прийнято",
    "videoAudioFinished": "Відео-аудіо завершено",
    "videoAudioMissed": "Відео-аудіо пропущено",
    "videoAudioRequested": "Відео-аудіо запитано",
    "videoCall": "Відеодзвінок",
    "videoCallAccepted": "Відеодзвінок прийнято",
    "videoCallFinished": "Відеодзвінок завершено",
    "videoCallMissed": "Відеодзвінок пропущено",
    "viewLess": "Дивитися менше",
    "viewMore": "Дивитися більше",
    "yourBrowserDoesNotSupportTheAudioElement": "Ваш браузер не підтримує аудіоелемент."
  },
  "confirmationDialog": {
    "acceptAndStartConsultation": "Прийняти та почати сесію?",
    "confirmationTitle": "Підтвердження!",
    "noText": "Скасувати",
    "yesText": "Підтвердити"
  },
  "consultation": {
    "aCall": "ДЗВІНОК",
    "anotherDoctorInCall": "Інший експерт зараз на дзвінку",
    "audioCall": "Аудіодзвінок",
    "callError": "Не вдалося ініціювати дзвінок, сервер повернув",
    "cameraSelection": "Вибір камери",
    "close": "Закрити",
    "configuration": "Налаштування",
    "expert_link": "Посилання для експерта",
    "joinAudioCall": "Приєднатися до аудіо",
    "joinVideoCall": "Приєднатися до відео",
    "microAndCameraConfiguration": "Налаштування мікрофона та камери",
    "microSelection": "Вибір мікрофона",
    "start": "ПОЧАТОК",
    "videoCall": "Відеодзвінок"
  },
  "consultations": {
    "attachement": "Вкладення",
    "closedBy": "Закрито",
    "consultationsHistory": "Історія консультацій",
    "duration": "Тривалість",
    "exportButton": "Експорт",
    "filters": "Фільтри",
    "guestTooltip": "Гість",
    "handledBy": "Оброблено",
    "inviteExpert": "Запросити колегу",
    "message": "Повідомлення",
    "newConsultation": "Нова консультація",
    "noConsultation": "Немає консультацій",
    "noPatientName": "Не визначено",
    "online": "Онлайн",
    "openedConsultation": "Відкриті консультації",
    "participant": "Учасник",
    "patient": "Користувач послуг",
    "requestedBy": "Запитано від",
    "sendAgainANewInvitation": "Повторно надіслати нове запрошення",
    "sendAgainTheInvitation": "Повторно надіслати запрошення",
    "share": "Поділитися запрошенням через електронну пошту або телефон",
    "shareBy": "Поділитися запрошенням за посиланням",
    "startDateTime": "Дата/час початку",
    "time": "Час",
    "translator": "Перекладач",
    "unread": "Непрочитані",
    "waitingQueue": "Черга очікування",
    "waitingRoom": "Зала очікування"
  },
  "dashboard": {
    "consultationsListAwaitingToBeClosedOrCompleted": "Список консультацій, які очікують на завершення або закриття",
    "consultationsListInAwaitingTreatment": "Список консультацій, що очікують на обробку",
    "dashboard": "Панель керування",
    "displayTheList": "Відобразити список",
    "message": "Повідомлення",
    "noConsultation": "Немає консультацій",
    "openedConsultations": "ВІДКРИТІ КОНСУЛЬТАЦІЇ",
    "patient": "Користувач послуг",
    "sendNewInvite": "Надіслати нове запрошення",
    "startNextConsultation": "Розпочати наступну консультацію",
    "time": "Час",
    "waitingRoom": "ЗАЛА ОЧІКУВАННЯ"
  },
  "error": {
    "blockedMessage": "Ваш запит був заблокований політикою безпеки. Будь ласка, зверніться до підтримки, якщо проблема зберігається.",
    "blockedTitle": "Запит заблоковано",
    "defaultMessage": "Сталася непередбачена помилка. Будь ласка, спробуйте пізніше.",
    "defaultTitle": "Помилка",
    "networkMessage": "Сталася помилка мережі. Перевірте підключення та спробуйте ще раз."
  },
  "filter": {
    "cancel": "Скасувати",
    "clear": "Очистити фільтри",
    "filters": "Фільтри",
    "filtersApplied": "Застосовані фільтри:",
    "handled_by": "Оброблено",
    "myself": "Я сам",
    "queue": "Черга",
    "sent_by": "Запрошення надіслано від",
    "somebodyElse": "Хтось інший"
  },
  "footer": {
    "supportedByThePrivateFoundation": "Підтримується приватним фондом"
  },
  "forgotPassword": {
    "backToLoginScreen": "Назад до екрану входу",
    "email": "Електронна пошта",
    "emailAddress": "Електронна адреса",
    "fillUpYourEmailAddressBellow": "Введіть вашу електронну адресу нижче, і ми надішлемо вам посилання для оновлення пароля.",
    "home": "ГОЛОВНА",
    "ifTheEmailProvidedExistsInOurDatabase": "Якщо зазначена електронна адреса є в нашій базі даних, ви отримаєте повідомлення з посиланням для оновлення пароля.",
    "pleaseProvideAValidEmail": "Будь ласка, введіть дійсну електронну адресу",
    "required": "обов'язково",
    "submit": "Підтвердити",
    "youForgotYourPassword": "Ви забули свій пароль:"
  },
  "invitations": {
    "accepted": "Прийнято",
    "acknowledged": "Визнано",
    "cancel": "Скасувати",
    "cancelRevoke": "Не видаляти",
    "cancelSendAgain": "Не надсилати повторно",
    "canceled": "Скасовано",
    "closed": "Закрито",
    "communicationMethod": "Спосіб спілкування",
    "confirmResend": "Ви впевнені, що хочете надіслати запрошення знову? Воно буде повторно надіслано тим же способом через той самий канал. Ця дія також скидає термін дії запрошень.",
    "confirmRevoke": "Ви впевнені, що хочете відкликати та видалити це запрошення? Жодного повідомлення користувачу послуг не буде надіслано.",
    "creationDate": "Дата створення",
    "delivered": "Доставлено",
    "edit": "Редагувати",
    "email": "Електронна пошта",
    "expertTooltip": "Експерт",
    "failed": "Не вдалося",
    "guestInvite": "Гість",
    "guestTooltip": "Гість",
    "immediately": "Негайно",
    "lastname": "Прізвище",
    "manual": "Посібник",
    "newInvite": "Нове запрошення",
    "next": "Наступне",
    "noConsultationInvite": "Немає запрошення на консультацію",
    "none": "Ніхто",
    "notDefined": "Не визначено",
    "partiallyDelivered": "Частково доставлено",
    "participant": "Учасник",
    "patient": "Користувач послуг",
    "pending": "В очікуванні",
    "phoneNumber": "Номер телефону",
    "previous": "Попереднє",
    "queued": "У черзі",
    "read": "Читати",
    "received": "Отримано",
    "receiving": "Отримання",
    "refused": "Відмовлено",
    "resendConfirmTitle": "Повторне надсилання посилання",
    "revoke": "Видалити",
    "revokeConfirmTitle": "Видалення запрошення",
    "scheduled": "Заплановано",
    "scheduledDate": "Запланована дата",
    "scheduledForInvite": "Заплановано для запрошення",
    "sendAgain": "Надіслати знову",
    "sendAgainTheSMSOrEmailInvite": "Надіслати знову SMS або електронне запрошення",
    "sending": "Відправка",
    "sent": "Надіслано",
    "sms": "СМС",
    "status": "Стан",
    "title": "ЗАПРОШЕННЯ",
    "translatorRequestInvite": "Перекладач",
    "undelivered": "Недоставлено",
    "whatsapp": "Whatsapp"
  },
  "inviteForm": {
    "aa": "Здалеку",
    "ab": "Абхазька",
    "ae": "Авестійська",
    "af": "Африканська",
    "ak": "Аканська",
    "am": "Вірменський",
    "an": "арагонська",
    "anotherExpert": "Додати іншого експерта",
    "ar": "Арабська",
    "as": "Асамська",
    "atLeastInviteGuestOrTranslator": "Ви повинні запросити хоча б одну третю сторону. Щоб запросити перекладача, змініть мову користувача послуг.",
    "av": "Аварська",
    "ay": "Аймарська",
    "ba": "Башкірська",
    "be": "Білоруська",
    "bg": "Болгарська",
    "bh": "Біхарі",
    "bi": "Біслама",
    "bm": "Бамбара",
    "bn": "Бенгальська",
    "bo": "тибетська",
    "br": "Бретонська",
    "bs": "Боснійська",
    "ca": "Каталанська",
    "cancel": "Скасувати",
    "cantUpdateAcceptedInvite": "Ви не можете редагувати запрошення, якщо його вже прийняв користувач послуг, перекладач або гість.",
    "ce": "Чеченська",
    "ch": "Чаморро",
    "chooseDate": "Оберіть дату",
    "chooseTime": "Оберіть час",
    "co": "Корсиканська",
    "consultationWillBeOnPremise": "Консультація буде проведена з користувачем послуг <strong> очно. </strong>",
    "cr": "Крі",
    "cs": "Чеська",
    "cu": "Старослов'янська церковна",
    "cv": "Чувашська",
    "cy": "Вельшська",
    "da": "Данська",
    "dateTime": "Дата і час",
    "de": "Німецька",
    "dv": "Дівехі",
    "dz": "Дзонгха",
    "editInvite": "Редагувати запрошення",
    "ee": "Ів",
    "el": "грецька",
    "emailOrSMS": "Електронна пошта або SMS",
    "en": "Англійська",
    "eo": "Есперанто",
    "es": "Іспанська",
    "et": "Естонська",
    "eu": "Баскська",
    "fa": "Перська",
    "female": "Жіноча",
    "ff": "Фула",
    "fi": "фінська",
    "firstName": "Ім'я",
    "firstNameIsRequired": "Ім'я є <strong> обов'язковим </strong>",
    "fj": "Фіджійська",
    "fo": "Фарерська",
    "fr": "Французька",
    "fy": "Західно-фризька",
    "ga": "Ірландська",
    "gd": "Шотландська гельська",
    "gl": "Галісійська",
    "gn": "Гуарані",
    "gu": "Гуджараті",
    "guests": "Гості",
    "gv": "Менкс",
    "ha": "Хауса",
    "he": "Іврит",
    "hi": "Хінді",
    "ho": "Хірі Моту",
    "hr": "Хорватська",
    "ht": "Гаїтянська",
    "hu": "Угорська",
    "hy": "Вірменська",
    "hz": "Гереро",
    "ia": "Міжмова",
    "id": "індонезійська",
    "ie": "міжмова",
    "ig": "Ігбо",
    "ii": "Сичуань І",
    "ik": "Інупіак",
    "invalidEmailAddress": "Недійсна електронна адреса",
    "invitationPatient": "Запрошення користувача послуг",
    "invitationThirdParty": "Інформація про користувача послуг",
    "invite": "Запросити",
    "inviteExpert": "Запросити колегу",
    "inviteLovedOneOrProfessional": "Запросіть близьку людину, доглядальника або перекладача",
    "inviteTranslator": "Запросити перекладача",
    "io": "Ідо",
    "is": "ісландська",
    "it": "Італійська",
    "iu": "Інуктітут",
    "ja": "Японська",
    "jv": "Яванська",
    "ka": "Грузинська",
    "kg": "Конго",
    "ki": "Кікуйю",
    "kj": "Кваньяма",
    "kk": "Казахська",
    "kl": "Гренландська",
    "km": "кхмерська",
    "kn": "Каннада",
    "ko": "Корейська",
    "kr": "Канурі",
    "ks": "Кашмірська",
    "ku": "Курдська",
    "kv": "Комі",
    "kw": "Корнійська",
    "ky": "Киргизька",
    "la": "Латинська",
    "language": "Мова",
    "lastName": "Прізвище",
    "lastNameIsRequired": "Прізвище є <strong> обов'язковим </strong>",
    "lb": "Люксембурзька",
    "lg": "Ганда",
    "li": "Лімбурзька",
    "linkSent": "Запрошення надіслано",
    "ln": "Лінгала",
    "lo": "Лаоська",
    "lt": "Литовська",
    "lu": "Люба",
    "lv": "Латвійська",
    "male": "Чоловіча",
    "mg": "Малагасійська",
    "mh": "Маршалльська",
    "mi": "Маорі",
    "mk": "македонська",
    "ml": "Малаялам",
    "mn": "монгольська",
    "mo": "Молдавська",
    "mr": "Маратхі",
    "ms": "Малайська",
    "mt": "мальтійська",
    "my": "Бірманська",
    "mySelf": "Ніхто",
    "na": "Науру",
    "nb": "норвезька букмол",
    "nd": "Північний Ндебеле",
    "ne": "Непальська",
    "ng": "Ндонга",
    "nl": "голландська",
    "nn": "Норвезький нюнорськ",
    "no": "норвезька",
    "notPermitted": "Цей номер телефону не дозволено використовувати на цій платформі.",
    "nr": "Південний Ндебеле",
    "nv": "Навахо",
    "ny": "Чічева",
    "oc": "Окситанська",
    "oj": "Оджибва",
    "om": "Оромо",
    "or": "Орія",
    "os": "Осетинська",
    "other": "Інше",
    "pa": "Панджабі",
    "patient": "Користувач послуг",
    "patientInvitationWillBeAfterTranslatorIsValidated": "Запрошення користувачу послуг або родичам не буде надіслано, поки перекладач не підтвердить запрошення.",
    "patientTeleConsultation": "Дистанційний користувач послуг",
    "patientTeleConsultationDescription": "Надішліть запрошення користувачу послуг для проведення телеконсультації. Ви також можете запросити перекладача, члена родини або іншого опікуна.",
    "pi": "Палі",
    "pl": "Польська",
    "pleaseChooseAWaitingQueue": "Будь ласка, оберіть чергу",
    "pleaseChooseLanguage": "Будь ласка, оберіть мову",
    "pleaseChooseOrganization": "Будь ласка, оберіть організацію",
    "pleaseChooseTheSex": "Будь ласка, оберіть стать",
    "pleaseEnterValidEmailOrPhoneNumber": "Будь ласка, введіть дійсну електронну пошту або номер телефону у форматі +41 або +33",
    "pleaseOnlyFillUpAnEmailOrAnMobilePhoneNumber": "Будь ласка, заповніть лише одну електронну адресу або номер телефону.",
    "pleaseOnlyFillUpAnEmailOrAnMobilePhoneNumberEx": "Будь ласка, введіть лише електронну пошту або номер телефону (+41 або +33)",
    "ps": "Пушту",
    "pt": "Португальська",
    "qu": "Кечуа",
    "remove": "Видалити",
    "required": "Обов'язково",
    "rm": "ретороманська",
    "rn": "Кірунді",
    "ro": "румунська",
    "ru": "Російська",
    "rw": "Кіньяруанда",
    "sa": "Санскрит",
    "sc": "Сардинська",
    "scheduledAt": "Заплановано на",
    "schedulingLater": "Запланувати пізніше",
    "sd": "Сіндхі",
    "se": "Північні саами",
    "selectTimezone": "Оберіть часовий пояс",
    "send": "Надіслати",
    "sendAnInvitation": "НАДІСЛАТИ ЗАПРОШЕННЯ",
    "sendLinkManually": "Я хочу надіслати посилання вручну",
    "sex": "Стать",
    "sg": "Санго",
    "sh": "Сербсько-хорватська",
    "si": "сингальська",
    "sk": "Словацька",
    "sl": "Словенська",
    "sm": "Самоанська",
    "sn": "Шона",
    "so": "Сомалі",
    "sq": "Албанська",
    "sr": "сербська",
    "ss": "Сваті",
    "st": "Сото",
    "su": "Сунданська",
    "sv": "Шведська",
    "sw": "Суахілі",
    "ta": "Тамільська",
    "te": "Телугу",
    "tg": "таджицька",
    "th": "Тайська",
    "thirdParty": "Третя сторона",
    "thirdPartyConsultation": "Користувач послуг особисто - Запрошення третій стороні",
    "thirdPartyConsultationDescription": "Користувач послуг перебуває на очній консультації. Надішліть запрошення перекладачу, члену родини або іншому опікуну.",
    "ti": "Тігринья",
    "tk": "Туркменська",
    "tl": "Тагальська",
    "tn": "Тсвана",
    "to": "Тонга",
    "tr": "Турецька",
    "translationOrganization": "Перекладацька організація",
    "ts": "Цонга",
    "tt": "Татарська",
    "tw": "Тві",
    "ty": "Таїтійська",
    "ug": "Уйгури",
    "uk": "Українська",
    "unknown": "Невідомо",
    "update": "Оновити",
    "ur": "Урду",
    "uz": "Узбецька",
    "ve": "Венда",
    "vi": "В'єтнамська",
    "vo": "Волапюк",
    "wa": "Валлонська",
    "waitingQueue": "Загальна черга очікування",
    "warningTranslatorMightBeLate": "Перекладач може відповісти з менш придатного місця, якщо запит зроблено менш ніж за 24 години до консультації.",
    "wo": "Волоф",
    "xh": "Коса",
    "yi": "Їдиш",
    "yo": "Йоруба",
    "za": "Джуанг",
    "zh": "Китайська",
    "zu": "Зулу"
  },
  "login": {
    "email": "Електронна пошта",
    "emailAddress": "Адреса електронної пошти",
    "home": "ГОЛОВНА",
    "iForgotMyPassword": "Я забув свій пароль",
    "institutionalConnection": "Інституційне підключення",
    "login": "Увійти",
    "loginWithALocalAccount": "Увійти з локальним обліковим записом:",
    "password": "Пароль",
    "pleaseFillUpTheRecievedSMS": "Будь ласка, введіть отриманий SMS-код:",
    "pleaseProvideAValidEmail": "Будь ласка, введіть дійсну адресу електронної пошти",
    "required": "обов'язково",
    "send": "Надіслати",
    "sendCodeAgain": "Надіслати код ще раз",
    "verificationCode": "Код підтвердження",
    "youReachedTheMaximumAttemptAmount": "Ви досягли максимальної кількості спроб"
  },
  "metadata": {
    "Age": "Вік",
    "Country": "Країна",
    "Facility": "Заклад",
    "FileID": "ID файлу"
  },
  "overlay": {
    "areYouSatisfiedWithTheHomeApp": "Чи допомогло вами використання {{branding}} покращити якість обслуговування, що надається цьому бенефіціару?",
    "close": "Закрити",
    "consultationSummary": "ПІДСУМОК КОНСУЛЬТАЦІЇ",
    "doNotCloseTheConsultation": "Не закривати консультацію",
    "doYouWantToLeaveUsAComment": "Хочете залишити нам коментар?",
    "duration": "Тривалість",
    "email": "Електронна пошта",
    "endDateTime": "Дата/час завершення",
    "none": "Ніхто",
    "notdefined": "Не визначено",
    "nurse": "Медсестра",
    "patientBirthday": "Дата народження користувача послуг",
    "patientFirstnameAndLastname": "Ім'я користувача послуг",
    "phoneNumber": "Номер телефону",
    "resume": "Продовжити",
    "sendMyFeedback": "Надіслати відгук",
    "sex": "Стать",
    "startDateTime": "Дата/час початку",
    "staryInTheCurrentConsultation": "Залишитися в поточній консультації",
    "takeOwnership": "Отримати право власності",
    "terminate": "ЗАВЕРШИТИ",
    "terminateButKeepOpened": "Завершити, але залишити відкритою",
    "thanksForYourFeedback": "Дякуємо за ваш відгук.",
    "theConsultation": "КОНСУЛЬТАЦІЮ",
    "theConsultationWillBeDisplayedIntoHistoryDuring24Hours": "Консультація буде відображатися в історії протягом 24 годин, і ви більше не зможете спілкуватися.",
    "youWillbeAbleToResumeTheConsultationLater": "Ви зможете продовжити консультацію пізніше, але медсестра чи користувач послуг більше не зможуть спілкуватися з вами.",
    "yourComment": "Ваш коментар"
  },
  "pdf": {
    "accepted": "прийнято",
    "attachedFile": "[Прикріплений файл]",
    "audioCall": "Аудіодзвінок",
    "call": "дзвінок",
    "chatHistory": "Історія чату",
    "closedBy": "Закрито",
    "consultationInformation": "Інформація про сесію",
    "consultationReport": "Звіт сесії",
    "doctorInformation": "Інформація про лікаря",
    "duration": "Тривалість",
    "endDateTime": "Дата/час завершення",
    "expertInformation": "Інформація про експерта",
    "fileName": "звіт_сесії",
    "finished": "завершено",
    "firstname": "Ім'я",
    "gender": "Стать",
    "lastname": "Прізвище",
    "missed": "пропущено",
    "patientInformation": "Інформація про пацієнта",
    "queue": "Черга",
    "requesterInformation": "Інформація про запитувача",
    "startDateTime": "Дата/час початку",
    "videoCall": "Відеодзвінок"
  },
  "planConsultation": {
    "alreadyStarted": "Вже розпочато",
    "goToConsultation": "Пропустити та перейти до сесії",
    "invalidUrl": "Недійсне посилання",
    "maxDelay": "Затримка не може перевищувати 60 хвилин",
    "send": "Надіслати",
    "success": "Успішно",
    "timeInMinutes": "Через (хвилини)",
    "tokenExpired": "Термін дії токена минув",
    "whenWillYouBeAvailable": "Коли ви будете доступні для консультації?"
  },
  "profile": {
    "addressEmail": "Електронна адреса",
    "disabled": "Вимкнено",
    "enable": "Увімкнути",
    "enabled": "Увімкнено",
    "enablesNotification": "Це увімкне сповіщення при запиті нової консультації.",
    "invalidNumber": "Недійсний номер",
    "invalidPhoneNumber": "Недійсний номер телефону (наприклад: +41...)",
    "lastname": "Прізвище",
    "messageServiceError": "Щось пішло не так",
    "messageServiceSuccess": "Успішно!",
    "mobilePhoneNumber": "Мобільний номер телефону",
    "name": "Ім'я",
    "notification": "Сповіщення",
    "notifications": "Сповіщення",
    "notificationsWhereNot": "Сповіщення не було",
    "numberNotSaved": "Номер не збережено",
    "numberSaved": "Номер збережено",
    "phoneNumber": "Номер телефону",
    "profile": "Профіль",
    "save": "Зберегти",
    "selectLanguage": "Мова",
    "sms": "SMS",
    "smsChallenge": "SMS-підтвердження",
    "smsNotification": "SMS-сповіщення",
    "updateTheProfile": "Оновити профіль",
    "whatsapp": "Whatsapp"
  },
  "profileUpdate": {
    "cancel": "Скасувати",
    "department": "Відділ",
    "enterDepartmentName": "Введіть назву відділу",
    "enterMobileNumber": "Введіть мобільний номер",
    "enterPatientFirstname": "Введіть ім'я користувача послуг",
    "enterPatientLastname": "Введіть прізвище користувача послуг",
    "firstname": "Ім'я",
    "lastname": "Прізвище",
    "mobilePhoneNumber": "Мобільний номер телефону",
    "pleaseFillUpThePhoneNumberWithFormat": "Будь ласка, введіть номер телефону у форматі +41XX...",
    "pleaseOnlyFillUpAnEmailOrAnMobilePhoneNumber": "Будь ласка, введіть лише одну електронну адресу або мобільний номер телефону",
    "required": "обов'язковим",
    "send": "Надіслати",
    "theFirstnameIs": "Ім'я є",
    "theLastnameIs": "Прізвище є",
    "updateTheProfile": "Оновити профіль"
  },
  "resetPassword": {
    "anUnknownErrorHasBeenEncountered": "Виникла невідома помилка. Будь ласка, спробуйте ще раз.",
    "backToLoginScreen": "Назад до екрану входу",
    "changePassword": "Змінити пароль",
    "home": "ГОЛОВНА",
    "iForgotMyPassword": "Я забув свій пароль.",
    "login": "Увійти",
    "newPassword": "Новий пароль",
    "password": "Пароль",
    "passwordQualityTooLow": "Якість пароля занадто низька",
    "required": "обов'язково",
    "save": "Зберегти",
    "theBothPasswordAreNotTheSame": "Обидва паролі не співпадають",
    "youAreOnThisPage": "Ви на цій сторінці, оскільки ви перейшли за посиланням для оновлення пароля. Будь ласка, введіть новий пароль нижче.",
    "yourPasswordHasBeenUpdated": "Ваш пароль було оновлено. Будь ласка, поверніться на сторінку входу, щоб використовувати ваш новий пароль.",
    "yourTokenHasExpired": "Термін дії вашого токена минув. Будь ласка, запросіть новий."
  },
  "roles": {
    "admin": "Адмін",
    "doctor": "Лікар",
    "nurse": "Медсестра",
    "patient": "Пацієнт",
    "requester": "Запитувач",
    "scheduler": "Планувальник"
  },
  "selectLanguage": {
    "en": "English",
    "fr": "Français",
    "sv": "Svenska",
    "uk": "Українська"
  },
  "sendInviteLink": {
    "close": "Закрити",
    "copied": "Скопійовано в буфер обміну",
    "label": "Посилання на запрошення",
    "sent": "Посилання на запрошення успішно надіслано учаснику",
    "subTitle": "Скопіюйте посилання нижче та поділіться ним з користувачем послуг зручним для вас способом. Увага: це посилання можна використати лише один раз.",
    "title": "Запросити за посиланням"
  },
  "sideChat": {
    "startTheConsultation": "Розпочати консультацію"
  },
  "testMedia": {
    "aProperlyTuned": "Правильно налаштований мікрофон повинен забезпечувати, щоб стрілка VU-метра знаходилася в зеленій центральній зоні під час розмови.",
    "cameraTest": "ТЕСТ КАМЕРИ",
    "microTest": "ТЕСТ МІКРОФОНА",
    "testError": "Тестування не вдалося, сервер повернув помилку"
  },
  "topNav": {
    "help": "Допомога",
    "logout": "Вийти",
    "new_consultation_form": "Форма нової консультації",
    "nurse": "Медсестра",
    "patientBirthday": "Дата народження користувача послуг",
    "patientFirstnameAndLastname": "Ім'я користувача послуг",
    "profile": "Профіль",
    "startTheNextConsultation": "Розпочати наступну консультацію",
    "terminateTheConsultation": "Завершити консультацію"
  },
  "tour": {
    "consultationsHistoryMenuContent": "Коли ви вирішите закрити консультацію, ваш користувач сервісу більше не зможе обмінюватися з вами повідомленнями. Консультація залишиться в цій історії протягом 24 годин, а потім буде видалена з системи з міркувань безпеки.",
    "consultationsHistoryMenuTitle": "Закриті консультації",
    "endBtnTitle": "Завершити",
    "endTourDescription": "Ви можете змінити мову або увімкнути SMS-сповіщення у випадку, якщо щось станеться, коли ви не підключені до цього додатку.",
    "endTourSubmitBtnTitle": "Ок",
    "endTourTitle": "Сторінка профілю",
    "headerProfileMenuContent": "Ви можете керувати деякою інформацією на сторінці вашого профілю.",
    "headerProfileMenuTitle": "Доступ до вашого профілю",
    "inviteFormContactInputContent": "Заповніть інформацію про користувача сервісу, щоб легко розпізнати, який користувач очікує на віддалену консультацію. Ви можете надіслати посилання на запрошення через SMS, email або WhatsApp залежно від конфігурації програмного забезпечення та країни користувача.",
    "inviteFormContactInputTitle": "Інформація про користувача сервісу",
    "inviteFormSendLinkManuallyContent": "Якщо ви віддаєте перевагу поділитися посиланням з користувачем сервісу вручну, відмітьте цей пункт. Після надсилання ви зможете скопіювати посилання та поділитися ним (наприклад, у листі, який ви напишете самостійно). Будьте обережні, не використовуйте посилання для тестування, оскільки посилання можна використати лише один раз.",
    "inviteFormSendLinkManuallyTitle": "Надіслати посилання вручну",
    "invitesMenuContent": "Тут ви можете переглянути або відкликати відкриті запрошення та надсилати нові запрошення для налаштування сесій {{branding}} з користувачами послуг або колегами.",
    "invitesMenuTitle": "Керування запрошеннями",
    "newInviteButtonContent": "Натисніть «запросити», щоб дозволити користувачу служби приєднатися до сеансу {{branding}}.",
    "newInviteButtonTitle": "Нове запрошення",
    "nextBtnTitle": "Далі",
    "openedConsultationsMenuContent": "Після проведення консультації ви можете залишити її відкритою, щоб користувач сервісу міг продовжувати спілкуватися з вами та надсилати повідомлення. Такі консультації можна переглядати у цьому розділі.",
    "openedConsultationsMenuTitle": "Довгострокові консультації",
    "prevBtnTitle": "Назад",
    "remotePatientInviteContent": "Натисніть 'Віддалений користувач', щоб користувач сервісу міг приєднатися до вас у цьому додатку.",
    "remotePatientInviteTitle": "Запросити віддаленого користувача сервісу",
    "startTourDescription": "{{branding}} допомагає вам підключатися до користувачів сервісу. Цей тур допоможе вам зрозуміти концепцію. Ви можете пропустити тур у будь-який момент, закривши цю допомогу.",
    "startTourDismissBtnTitle": "Пропустити тур",
    "startTourSubmitBtnTitle": "Далі",
    "startTourTitle": "Ласкаво просимо до {{branding}}",
    "waitingRoomMenuContent": "Як тільки ваш користувач сервісу скористається посиланням і запросить приєднатися до консультації, ви отримаєте сповіщення зі звуком і побачите користувача у цій черзі. Тримайте додаток відкритим, щоб зменшити ризик пропустити консультацію.",
    "waitingRoomMenuTitle": "Зал очікування користувачів сервісу"
  }
}
